asciicast/__init__.py
asciicast/cast.py
asciicast/cli.py
asciicast-0.1.1.dist-info/AUTHORS.rst
asciicast-0.1.1.dist-info/LICENSE
asciicast-0.1.1.dist-info/METADATA
asciicast-0.1.1.dist-info/WHEEL
asciicast-0.1.1.dist-info/RECORD
