Metadata-Version: 2.1
Name: asciicast
Version: 0.1.1
Summary: Top-level package for asciicast.
Home-page: https://github.com/abilian/asciicast
Author: Abilian SAS
Author-email: sf@abilian.com
Requires-Python: >=3.10,<4
Classifier: Development Status :: 2 - Pre-Alpha
Classifier: Intended Audience :: Developers
Classifier: Natural Language :: English
Classifier: Programming Language :: Python :: 3
Classifier: Programming Language :: Python :: 3.10
Classifier: Programming Language :: Python :: 3.11
Classifier: Programming Language :: Python :: 3.12
Classifier: Programming Language :: Python :: 3.8
Classifier: Programming Language :: Python :: 3.9
Requires-Dist: asciinema (>=2.2.0,<3.0.0)
Requires-Dist: attrs (>=23,<24)
Requires-Dist: click (>=8.1.3,<9.0.0)
